SEQLinkage/Core.py
SEQLinkage/Linkage.py
SEQLinkage/Main.py
SEQLinkage/Plot.py
SEQLinkage/Runner.py
SEQLinkage/Utils.py
SEQLinkage/__init__.py
SEQLinkage/_nbdev.py
SEQLinkage/seqlink.py
SEQLinkage-2.0.4.dist-info/LICENSE
SEQLinkage-2.0.4.dist-info/METADATA
SEQLinkage-2.0.4.dist-info/WHEEL
SEQLinkage-2.0.4.dist-info/entry_points.txt
SEQLinkage-2.0.4.dist-info/top_level.txt
SEQLinkage-2.0.4.dist-info/RECORD
