Metadata-Version: 2.1
Name: SEQLinkage
Version: 2.0.4
Summary: Collapsed Haplotype Pattern Method for Linkage Analysis of Next-Generation Sequencing Data
Home-page: https://github.com/changebio/SEQLinkage/tree/master/
Author: Yin Huang, Gao Wang
Author-email: changebio@yeah.net
License: Apache Software License 2.0
Keywords: CHP Linkage Analysis
Platform: UNKNOWN
Classifier: Development Status :: 3 - Alpha
Classifier: Intended Audience :: Developers
Classifier: Natural Language :: English
Classifier: Programming Language :: Python :: 3.6
Classifier: Programming Language :: Python :: 3.7
Classifier: Programming Language :: Python :: 3.8
Classifier: License :: OSI Approved :: Apache Software License
Requires-Python: >=3.6
License-File: LICENSE
Requires-Dist: pip
Requires-Dist: packaging
Requires-Dist: numpy
Requires-Dist: pandas
Requires-Dist: scipy
Requires-Dist: matplotlib
Requires-Dist: rpy2
Provides-Extra: dev
